mprov_jobserver/__init__.py
mprov_jobserver/app.py
mprov_jobserver/jobserver.yaml
mprov_jobserver/main.py
mprov_jobserver/mprov_jobserver
mprov_jobserver/script.py
mprov_jobserver/plugins/__init__.py
mprov_jobserver/plugins/dnsmasq.py
mprov_jobserver/plugins/dnsmasq.yaml
mprov_jobserver/plugins/image-delete.yaml
mprov_jobserver/plugins/image-sync.yaml
mprov_jobserver/plugins/image-update.yaml
mprov_jobserver/plugins/image_delete.py
mprov_jobserver/plugins/image_sync.py
mprov_jobserver/plugins/image_update.py
mprov_jobserver/plugins/libgenders.py
mprov_jobserver/plugins/mprov-webserver.yaml
mprov_jobserver/plugins/mprov_webserver.py
mprov_jobserver/plugins/nads.py
mprov_jobserver/plugins/nads.yaml
mprov_jobserver/plugins/plugin.py
mprov_jobserver/plugins/repo-delete.yaml
mprov_jobserver/plugins/repo-update.yaml
mprov_jobserver/plugins/repo_delete.py
mprov_jobserver/plugins/repo_sync.py
mprov_jobserver/plugins/repo_update.py
mprov_jobserver/plugins/script-runner.yaml
mprov_jobserver/plugins/script_runner.py
mprov_jobserver/plugins/dnsmasq_mod/__init__.py
mprov_jobserver/plugins/dnsmasq_mod/config.py
mprov_jobserver/plugins/dnsmasq_mod/dhcp.py
mprov_jobserver/plugins/dnsmasq_mod/dns.py
mprov_jobserver/plugins/image_update_mod/__init__.py
mprov_jobserver/plugins/image_update_mod/rhel.py
mprov_jobserver/plugins/repo_update_mod/__init__.py
mprov_jobserver/plugins/repo_update_mod/rhel.py
mprov_jobserver/templates/dnsmasq/dhcp.conf.j2
mprov_jobserver/templates/dnsmasq/dhcp_host.conf.j2
mprov_jobserver/templates/dnsmasq/dns.conf.j2
mprov_jobserver/templates/dnsmasq/dns_host.conf.j2
mprov_jobserver/templates/dnsmasq/ipversionrouter.ipxe.j2
mprov_jobserver/templates/dnsmasq/ipxe.conf.j2
mprov_jobserver/templates/dnsmasq/menu.ipxe.j2
mprov_jobserver/templates/image-update/script-runner.sh
mprov_jobserver/templates/image-update/script-runner.yaml.j2
mprov_jobserver-0.0.59.data/scripts/mprov_jobserver
mprov_jobserver-0.0.59.dist-info/LICENSE
mprov_jobserver-0.0.59.dist-info/METADATA
mprov_jobserver-0.0.59.dist-info/WHEEL
mprov_jobserver-0.0.59.dist-info/top_level.txt
mprov_jobserver-0.0.59.dist-info/RECORD
