Metadata-Version: 2.1
Name: mprov_jobserver
Version: 0.0.59
Summary: The job server component of mProv
Home-page: https://github.com/mprov-ng/mprov_jobserver
Author: Jason Williams
Author-email: jasonw@jhu.edu
Project-URL: Bug Tracker, https://github.com/mprov-ng/mprov_jobserver/issues
Classifier: Programming Language :: Python :: 3.8
Classifier: Programming Language :: Python :: 3.9
Classifier: Programming Language :: Python :: 3.10
Classifier: Programming Language :: Python :: 3.11
Classifier: Programming Language :: Python :: 3.12
Classifier: Operating System :: POSIX :: Linux
Classifier: License :: OSI Approved :: Apache Software License
Requires-Python: >=3.8
License-File: LICENSE
Requires-Dist: pyyaml
Requires-Dist: jinja2
Requires-Dist: requests
Requires-Dist: python-slugify
Requires-Dist: py-dmidecode
Requires-Dist: netifaces
Requires-Dist: pyparted ==3.11.7
Requires-Dist: sh
Requires-Dist: pyroute2 ==0.8.1
Requires-Dist: dnspython
Requires-Dist: distro
Requires-Dist: psutil
